{
  "ComponentIndexes": {},
  "ControlUniqueGuids": {},
  "ControlUniqueIds": {
    "App": 1,
    "Button1": 8,
    "Group1": 14,
    "Group2": 15,
    "Icon1": 9,
    "Icon2": 11,
    "Icon3": 20,
    "Image1": 5,
    "Image3": 19,
    "Label1": 10,
    "Label1_1": 13,
    "Rectangle1": 4,
    "Rectangle2": 6,
    "Rectangle3": 7,
    "Rectangle3_1": 12,
    "Screen1": 3
  },
  "FunctionParamsInvariantScripts": {},
  "FunctionParamsInvariantScriptsOnInstances": {},
  "HeaderLastSavedDateTimeUTC": "03/22/2023 09:27:17",
  "IsLegacyComponentAllowGlobalScopeCase": false,
  "LocalConnectionIDReferences": {},
  "LocalDatabaseReferencesAsEmpty": false,
  "LocalResourceFileNames": {
    "D": "6b11cdb6-d01a-4bd9-920c-01db0d5a9248.png",
    "DigiMantra-Labs-logo-design-New (1)": "0001.png"
  },
  "LocalResourceRootPaths": {
    "D": "https://docserverpwaprodcin.blob.core.windows.net/8a5bbbce-4146-4e37-923f-b880987c100f-1/resource/23e2a751-e84a-48d3-a312-0c5ee5a00bd8.png?sv=2018-03-28&sr=b&sig=l5u5Glmz8dwBaZ5kHOhO1TecBoz8JkCY28kbndSyxhM%3D&spr=https&se=2023-03-23T09%3A28%3A49Z&sp=r",
    "DigiMantra-Labs-logo-design-New (1)": "https://docserverpwaprodcin.blob.core.windows.net/8a5bbbce-4146-4e37-923f-b880987c100f-1/resource/Assets0Images00001.png?sv=2018-03-28&sr=b&sig=LzAI9CR3U7sEyc6VXETBA7KmuuaMF5GIOjdsPzRWd1Y%3D&spr=https&se=2023-03-23T08%3A08%3A34Z&sp=r"
  },
  "OrderComponentMetadata": {},
  "OrderComponentTemplate": {},
  "OrderDataSource": {
    "ComboBoxSample": 0,
    "DropDownSample": 1
  },
  "OrderGroupControls": {
    "Group1": {
      "Icon1": 1,
      "Label1": 0,
      "Rectangle3": 2
    },
    "Group2": {
      "Icon2": 0,
      "Label1_1": 1,
      "Rectangle3_1": 2
    }
  },
  "OrderPcfTemplate": {},
  "OrderTemplate": {},
  "OrderXMLTemplate": {
    "button": 3,
    "icon": 2,
    "image": 1,
    "label": 4,
    "rectangle": 0
  },
  "OverridablePropertiesEntry": {
    "App": {},
    "Button1": {},
    "Group1": {},
    "Group2": {},
    "Icon1": {},
    "Icon2": {},
    "Icon3": {},
    "Image1": {},
    "Image3": {},
    "Label1": {},
    "Label1_1": {},
    "Rectangle1": {},
    "Rectangle2": {},
    "Rectangle3": {},
    "Rectangle3_1": {},
    "Screen1": {}
  },
  "PCFDynamicSchemaForIRRetrievalEntry": {},
  "PCFTemplateEntry": {},
  "PublishOrderIndices": {
    "App": 0,
    "Button1": 7,
    "Group1": 6,
    "Group2": 10,
    "Icon1": 8,
    "Icon2": 11,
    "Icon3": 3,
    "Image1": 1,
    "Image3": 4,
    "Label1": 9,
    "Label1_1": 13,
    "Rectangle1": 0,
    "Rectangle2": 2,
    "Rectangle3": 5,
    "Rectangle3_1": 12,
    "Screen1": 2
  },
  "ResourcesJsonIndices": {
    "Image-D": 2,
    "Image-DigiMantra-Labs-logo-design-New (1)": 1,
    "Image-SampleImage": 0
  },
  "RuleScreenIdWithoutScreen": {},
  "TemplateVersions": {},
  "VolatileProperties": {
    "AnalysisLoadTime": 0.0869921,
    "ControlCount": {
      "button": 1,
      "group": 2,
      "icon": 2,
      "image": 1,
      "label": 2,
      "rectangle": 4,
      "screen": 1
    },
    "DeserializationLoadTime": 0.5209821,
    "ErrorCount": 0
  },
  "WasLocalDatabaseReferencesEmpty": true
}